github_random_star/__init__.py
github_random_star/api.py
github_random_star/commands/__init__.py
github_random_star/commands/meta.py
github_random_star/commands/repo.py
github_random_star/commands/star.py
github_random_star/extension.py
github_random_star/utility.py
github_random_star/version.py
github_random_star-1.2.0.dist-info/LICENSE.md
github_random_star-1.2.0.dist-info/METADATA
github_random_star-1.2.0.dist-info/WHEEL
github_random_star-1.2.0.dist-info/entry_points.txt
github_random_star-1.2.0.dist-info/RECORD
