Metadata-Version: 2.1
Name: github-random-star
Version: 1.2.0
Summary: Simple CLI tool to fetch random starred repositories from a users GitHub profile.
License: MIT
Keywords: python,python3,cli,github,git
Author: David Kasakaitis
Author-email: davidkasakaitis@proton.me
Requires-Python: >=3.10,<4.0
Classifier: Development Status :: 5 - Production/Stable
Classifier: Environment :: Console
Classifier: Intended Audience :: Developers
Classifier: Intended Audience :: Information Technology
Classifier: Intended Audience :: System Administrators
Classifier: License :: OSI Approved :: MIT License
Classifier: Natural Language :: English
Classifier: Programming Language :: Python :: 3
Classifier: Programming Language :: Python :: 3.10
Classifier: Programming Language :: Python :: 3.11
Classifier: Programming Language :: Python :: 3.12
Classifier: Programming Language :: Python :: 3.13
Classifier: Topic :: Software Development :: Version Control :: Git
Classifier: Topic :: Utilities
Classifier: Typing :: Typed
Requires-Dist: cleo (>=2.1.0,<3.0.0)
Requires-Dist: httpx (>=0.26.0,<0.27.0)
Project-URL: Bug Tracker, https://github.com/ddkasa/gh-random-star/issues
Project-URL: Homepage, https://github.com/ddkasa/gh-random-star
Project-URL: Source, https://github.com/ddkasa/gh-random-star
